mqtt/__init__.py
mqtt/consumer.py
mqtt/producer.py
mqtt_coordinated-0.0.2.dist-info/METADATA
mqtt_coordinated-0.0.2.dist-info/RECORD
mqtt_coordinated-0.0.2.dist-info/WHEEL
mqtt_coordinated-0.0.2.dist-info/top_level.txt
utils/__init__.py
utils/constants.py
utils/graceful_killer.py
