Metadata-Version: 2.1
Name: mqtt-coordinated
Version: 0.0.2
Summary: Coordinated Producer Consumer for MQTT
Home-page: https://github.com/lprashant-94/mqtt-coordinator-consumer
Author: Prashant Lokhande
Author-email: lprashant94@gmail.com
License: UNKNOWN
Platform: UNKNOWN
Classifier: Programming Language :: Python :: 2
Classifier: Operating System :: OS Independent
